features_creator/__init__.py
features_creator/features_creator.py
features_creator-1.1.3.dist-info/LICENSE
features_creator-1.1.3.dist-info/WHEEL
features_creator-1.1.3.dist-info/METADATA
features_creator-1.1.3.dist-info/RECORD
