Metadata-Version: 2.1
Name: features-creator
Version: 1.1.3
Summary: Helper functions to create new features.
License: MIT
Author: DSCI_524_GROUP26
Requires-Python: >=3.9,<4.0
Classifier: License :: OSI Approved :: MIT License
Classifier: Programming Language :: Python :: 3
Classifier: Programming Language :: Python :: 3.10
Classifier: Programming Language :: Python :: 3.9
Requires-Dist: Sphinx (>=4.4.0,<5.0.0)
Requires-Dist: numpy (>=1.22.1,<2.0.0)
Requires-Dist: pandas (>=1.3.5,<2.0.0)
